kulgap/__init__.py
kulgap/collection.py
kulgap/config.py
kulgap/errors.py
kulgap/metadata.py
kulgap/metrics.py
kulgap/plotting.py
kulgap/source.py
kulgap/utils.py
kulgap-0.1.0.dev0.dist-info/METADATA
kulgap-0.1.0.dev0.dist-info/RECORD
kulgap-0.1.0.dev0.dist-info/WHEEL
kulgap-0.1.0.dev0.dist-info/top_level.txt
