Metadata-Version: 2.1
Name: kulgap
Version: 0.1.0.dev0
Summary: UNKNOWN
Home-page: https://github.com/itselijahtai/kulgap
Author: Elijah Tai, Janosch Ortmann
Author-email: elijah.tai@outlook.com
License: MIT
Platform: UNKNOWN
Requires-Dist: pandas
Requires-Dist: numpy
Requires-Dist: scipy
Requires-Dist: GPy
Requires-Dist: matplotlib
Requires-Dist: mypy
